{"id":"b74807a9-6a56-4c1a-aed3-55cf5fd6c359","timestamp":1751362215521,"matcher":{"static":{"/__nuxt_content/index/sql_dump.txt":{"prerender":true},"/__nuxt_content/projects/sql_dump.txt":{"prerender":true},"/__nuxt_content/blog/sql_dump.txt":{"prerender":true},"/__nuxt_content/pages/sql_dump.txt":{"prerender":true},"/__nuxt_content/speaking/sql_dump.txt":{"prerender":true},"/__nuxt_content/about/sql_dump.txt":{"prerender":true},"/__nuxt_content/gallery/sql_dump.txt":{"prerender":true},"/__nuxt_content/services/sql_dump.txt":{"prerender":true}},"wildcard":{},"dynamic":{}},"prerendered":["/","/blog","/speaking","/blog/pravila-passajira","/projects","/about"]}